punxa/__init__.py
punxa/assembly.py
punxa/bus.py
punxa/clint.py
punxa/csr.py
punxa/custom_instruction.py
punxa/fpu.py
punxa/instruction_decode.py
punxa/interactive_commands.py
punxa/memory.py
punxa/plic.py
punxa/processor_exceptions.py
punxa/serialize.py
punxa/temp_helper.py
punxa/tracing.py
punxa/uart.py
punxa-2025.1.dist-info/licenses/LICENSE
punxa-2025.1.dist-info/METADATA
punxa-2025.1.dist-info/WHEEL
punxa-2025.1.dist-info/top_level.txt
punxa-2025.1.dist-info/RECORD
