Metadata-Version: 2.4
Name: punxa
Version: 2025.1
Summary: Python-based RISC-V Full System Simulator.
Home-page: https://github.com/davidcastells/punxa
Author: David Castells-Rufas
Author-email: David Castells-Rufas <david.castells@uab.cat>
License-File: LICENSE
Requires-Dist: py4hw>=2025.4
Requires-Dist: pyelftools
Requires-Dist: itanium-demangler
Dynamic: author
Dynamic: home-page
Dynamic: license-file
